tpln/__init__.py
tpln/__main__.py
tpln/flow.py
tpln/tasks/__init__.py
tpln/tasks/base_task.py
tpln/tasks/shell_task.py
tpln/tasks/sleep_task.py
python_tpln-0.1.0.dist-info/WHEEL
python_tpln-0.1.0.dist-info/METADATA
python_tpln-0.1.0.dist-info/RECORD
